happy_bank_core/__init__.py
happy_bank_core/app.py
happy_bank_core/cli/__init__.py
happy_bank_core/cli/cli.py
happy_bank_core/config/__init__.py
happy_bank_core/config/log.py
happy_bank_core/data/__init__.py
happy_bank_core/data/connector.py
happy_bank_core/data/file_connector.py
happy_bank_core/data/memory_connector.py
happy_bank_core/logic/__init__.py
happy_bank_core/logic/account.py
happy_bank_core/logic/registration.py
happy_bank_core/logic/transaction.py
happy_bank_core-0.7.0.dist-info/entry_points.txt
happy_bank_core-0.7.0.dist-info/LICENSE
happy_bank_core-0.7.0.dist-info/WHEEL
happy_bank_core-0.7.0.dist-info/METADATA
happy_bank_core-0.7.0.dist-info/RECORD
