Metadata-Version: 2.1
Name: happy-bank-core
Version: 0.7.0
Summary: A simple bank core app for mentoring purpose
License: MIT
Author: JanMate
Author-email: JanMate@github.com
Requires-Python: >=3.9
Classifier: License :: OSI Approved :: MIT License
Classifier: Programming Language :: Python :: 3
Classifier: Programming Language :: Python :: 3.10
Classifier: Programming Language :: Python :: 3.9
Requires-Dist: Flask (>=2.0,<3.0)
Requires-Dist: click (>=8.0,<9.0)
Requires-Dist: toml (>=0.10.1,<0.11.0)
